odoo/addons/web_listview_invert_selection/README.rst
odoo/addons/web_listview_invert_selection/__init__.py
odoo/addons/web_listview_invert_selection/__manifest__.py
odoo/addons/web_listview_invert_selection/i18n/fr.po
odoo/addons/web_listview_invert_selection/i18n/web_listview_invert_selection.pot
odoo/addons/web_listview_invert_selection/static/description/after.png
odoo/addons/web_listview_invert_selection/static/description/before.png
odoo/addons/web_listview_invert_selection/static/description/icon.png
odoo/addons/web_listview_invert_selection/static/src/js/web_listview_invert_selection.js
odoo/addons/web_listview_invert_selection/static/src/less/web_listview_invert_selection.less
odoo/addons/web_listview_invert_selection/templates/assets.xml
odoo11_addon_web_listview_invert_selection-11.0.1.0.0.99.dev3.dist-info/METADATA
odoo11_addon_web_listview_invert_selection-11.0.1.0.0.99.dev3.dist-info/RECORD
odoo11_addon_web_listview_invert_selection-11.0.1.0.0.99.dev3.dist-info/WHEEL
odoo11_addon_web_listview_invert_selection-11.0.1.0.0.99.dev3.dist-info/top_level.txt
